numtostr_rus/__init__.py
numtostr_rus/converter.py
numtostr_rus/db.py
numtostr_rus/mult.py
numtostr_rus-1.0.1.dist-info/METADATA
numtostr_rus-1.0.1.dist-info/WHEEL
numtostr_rus-1.0.1.dist-info/licenses/LICENSE
numtostr_rus-1.0.1.dist-info/RECORD
