Metadata-Version: 2.1
Name: numtostr-rus
Version: 1.0.1
Summary: Simple python number-to-russian-string converter
Project-URL: Homepage, https://github.com/Avorthoren/numtostr_rus
Project-URL: Bug Tracker, https://github.com/Avorthoren/numtostr_rus/issues
Author-email: Victor Podust <undefeatvip@gmail.com>
License: Copyright (c) 2022 Victor Podust
Classifier: License :: OSI Approved :: MIT License
Classifier: Operating System :: OS Independent
Classifier: Programming Language :: Python :: 3.10
Classifier: Programming Language :: Python :: 3.6
Classifier: Programming Language :: Python :: 3.7
Classifier: Programming Language :: Python :: 3.8
Classifier: Programming Language :: Python :: 3.9
Requires-Python: >=3.6.2
